logoo/__init__.py
logoo/data.py
logoo/logger.py
logoo/primary_logger.py
logoo-1.6.0.dist-info/LICENSE
logoo-1.6.0.dist-info/METADATA
logoo-1.6.0.dist-info/WHEEL
logoo-1.6.0.dist-info/top_level.txt
logoo-1.6.0.dist-info/RECORD
