Metadata-Version: 2.1
Name: logoo
Version: 1.6.0
Summary: Openobserve log ingestion made simple.
Author: Skelmis
Author-email: skelmis.craft@gmail.com
Project-URL: Issue tracker, https://github.com/Skelmis/logoo/issues
Project-URL: Homepage, https://github.com/Skelmis/logoo
Classifier: Programming Language :: Python :: 3
Classifier: License :: OSI Approved :: MIT License
Classifier: Operating System :: OS Independent
Requires-Python: >=3.10
License-File: LICENSE
Requires-Dist: httpx
Requires-Dist: orjson
Requires-Dist: skelmis-commons >=1.1.0
